<?xml version="1.0" encoding="utf-8"?><soap:Envelope xmlns:soap="http://www.w3.org/2003/05/soap-envelope" xmlns:xsi="http://www.w3.org/2001/XMLSchema-instance" xmlns:xsd="http://www.w3.org/2001/XMLSchema"><soap:Header><FEHeaderInfo xmlns="http://ar.gov.afip.dif.FEV1/"><ambiente>Produccion - Sae</ambiente><fecha>2023-05-30T11:04:12.5976596-03:00</fecha><id>5.2.1.0</id></FEHeaderInfo></soap:Header><soap:Body><FECompUltimoAutorizadoResponse xmlns="http://ar.gov.afip.dif.FEV1/"><FECompUltimoAutorizadoResult><PtoVta>4</PtoVta><CbteTipo>1</CbteTipo><CbteNro>17729</CbteNro></FECompUltimoAutorizadoResult></FECompUltimoAutorizadoResponse></soap:Body></soap:Envelope>
